LICENSE
MANIFEST.in
README.md
setup.py
drf_autodocs/__init__.py
drf_autodocs/decorators.py
drf_autodocs/endpoint.py
drf_autodocs/parser.py
drf_autodocs/urls.py
drf_autodocs/views.py
drf_autodocs/builtin_docs/__init__.py
drf_autodocs/static/css/custom.css
drf_autodocs/static/css/materialize.min.css
drf_autodocs/static/img/favicon.ico
drf_autodocs/static/js/jquery-2.1.1.min.js
drf_autodocs/static/js/materialize.min.js
drf_autodocs/templates/drf_autodocs/index.html
drf_autodocs/templates/drf_autodocs/components/fields_list.html
drf_autodocs/templates/drf_autodocs/components/tree_node.html
drf_autodocs/templatetags/__init__.py
drf_autodocs/templatetags/autodocs_filters.py
drf_autodocs/util/__init__.py
drf_autodocs/util/rendering.py
mindbogglr_drf_autodocs.egg-info/PKG-INFO
mindbogglr_drf_autodocs.egg-info/SOURCES.txt
mindbogglr_drf_autodocs.egg-info/dependency_links.txt
mindbogglr_drf_autodocs.egg-info/requires.txt
mindbogglr_drf_autodocs.egg-info/top_level.txt