Metadata-Version: 1.1
Name: mindbogglr-drf-autodocs
Version: 0.4.3.1
Summary: Extensible auto django rest framework api generator
Home-page: https://github.com/iMakedonsky/drf-autodocs
Author: Mashianov Oleksander
Author-email: mashianov@gmail.com
License: BSD
Platform: UNKNOWN
Classifier: Development Status :: 5 - Production/Stable
Classifier: Environment :: Web Environment
Classifier: Framework :: Django
Classifier: Intended Audience :: Developers
Classifier: License :: OSI Approved :: BSD License
Classifier: Operating System :: OS Independent
Classifier: Programming Language :: Python
Classifier: Programming Language :: Python :: 3
Classifier: Programming Language :: Python :: 3.4
Classifier: Programming Language :: Python :: 3.5
